{"trial_id": "e45ef8caaee8529585f2c9ae6eba88fb", "hyperparameters": {"space": [{"class_name": "Boolean", "config": {"name": "structured_data_block_1/normalize", "default": false, "conditions": []}}, {"class_name": "Boolean", "config": {"name": "structured_data_block_1/dense_block_1/use_batchnorm", "default": false, "conditions": []}}, {"class_name": "Choice", "config": {"name": "structured_data_block_1/dense_block_1/num_layers", "default": 2, "conditions": [], "values": [1, 2, 3], "ordered": true}}, {"class_name": "Choice", "config": {"name": "structured_data_block_1/dense_block_1/units_0", "default": 32, "conditions": [], "values": [16, 32, 64, 128, 256, 512, 1024], "ordered": true}}, {"class_name": "Choice", "config": {"name": "structured_data_block_1/dense_block_1/dropout", "default": 0.0, "conditions": [], "values": [0.0, 0.25, 0.5], "ordered": true}}, {"class_name": "Choice", "config": {"name": "structured_data_block_1/dense_block_1/units_1", "default": 32, "conditions": [], "values": [16, 32, 64, 128, 256, 512, 1024], "ordered": true}}, {"class_name": "Choice", "config": {"name": "regression_head_1/dropout", "default": 0, "conditions": [], "values": [0.0, 0.25, 0.5], "ordered": true}}, {"class_name": "Choice", "config": {"name": "optimizer", "default": "adam", "conditions": [], "values": ["adam", "sgd", "adam_weight_decay"], "ordered": false}}, {"class_name": "Choice", "config": {"name": "learning_rate", "default": 0.001, "conditions": [], "values": [0.1, 0.01, 0.001, 0.0001, 2e-05, 1e-05], "ordered": true}}, {"class_name": "Choice", "config": {"name": "structured_data_block_1/dense_block_1/units_2", "default": 32, "conditions": [], "values": [16, 32, 64, 128, 256, 512, 1024], "ordered": true}}], "values": {"structured_data_block_1/normalize": true, "structured_data_block_1/dense_block_1/use_batchnorm": true, "structured_data_block_1/dense_block_1/num_layers": 2, "structured_data_block_1/dense_block_1/units_0": 16, "structured_data_block_1/dense_block_1/dropout": 0.0, "structured_data_block_1/dense_block_1/units_1": 128, "regression_head_1/dropout": 0.0, "optimizer": "adam", "learning_rate": 0.001, "structured_data_block_1/dense_block_1/units_2": 256}}, "metrics": {"metrics": {"loss": {"direction": "min", "observations": [{"value": [86.3537368774414], "step": 0}, {"value": [86.05999755859375], "step": 1}, {"value": [85.77359008789062], "step": 2}, {"value": [85.48838806152344], "step": 3}, {"value": [85.20307159423828], "step": 4}, {"value": [84.91777038574219], "step": 5}, {"value": [84.63232421875], "step": 6}, {"value": [84.34586334228516], "step": 7}, {"value": [84.05834197998047], "step": 8}, {"value": [83.76953125], "step": 9}, {"value": [83.47925567626953], "step": 10}, {"value": [83.18685150146484], "step": 11}, {"value": [82.89253234863281], "step": 12}, {"value": [82.59579467773438], "step": 13}, {"value": [82.29606628417969], "step": 14}, {"value": [81.99263000488281], "step": 15}, {"value": [81.68640899658203], "step": 16}, {"value": [81.37677001953125], "step": 17}, {"value": [81.06367492675781], "step": 18}, {"value": [80.74691009521484], "step": 19}, {"value": [80.42570495605469], "step": 20}, {"value": [80.09962463378906], "step": 21}, {"value": [79.76897430419922], "step": 22}, {"value": [79.43356323242188], "step": 23}, {"value": [79.0928955078125], "step": 24}, {"value": [78.74655151367188], "step": 25}, {"value": [78.39445495605469], "step": 26}, {"value": [78.03623962402344], "step": 27}, {"value": [77.67223358154297], "step": 28}, {"value": [77.30209350585938], "step": 29}, {"value": [76.92550659179688], "step": 30}, {"value": [76.54218292236328], "step": 31}, {"value": [76.15229034423828], "step": 32}, {"value": [75.75575256347656], "step": 33}, {"value": [75.35224914550781], "step": 34}, {"value": [74.94145965576172], "step": 35}, {"value": [74.52359771728516], "step": 36}, {"value": [74.09803771972656], "step": 37}, {"value": [73.66426086425781], "step": 38}, {"value": [73.22270202636719], "step": 39}, {"value": [72.77315521240234], "step": 40}, {"value": [72.31570434570312], "step": 41}, {"value": [71.85014343261719], "step": 42}, {"value": [71.37596130371094], "step": 43}, {"value": [70.89310455322266], "step": 44}, {"value": [70.40147399902344], "step": 45}, {"value": [69.90120697021484], "step": 46}, {"value": [69.39238739013672], "step": 47}, {"value": [68.874755859375], "step": 48}, {"value": [68.3487777709961], "step": 49}, {"value": [67.8144760131836], "step": 50}, {"value": [67.27113342285156], "step": 51}, {"value": [66.7185287475586], "step": 52}, {"value": [66.15746307373047], "step": 53}, {"value": [65.58733367919922], "step": 54}, {"value": [65.00809478759766], "step": 55}, {"value": [64.41903686523438], "step": 56}, {"value": [63.819801330566406], "step": 57}, {"value": [63.21040725708008], "step": 58}, {"value": [62.59160614013672], "step": 59}, {"value": [61.96281433105469], "step": 60}, {"value": [61.3234748840332], "step": 61}, {"value": [60.67357635498047], "step": 62}, {"value": [60.01285934448242], "step": 63}, {"value": [59.341827392578125], "step": 64}, {"value": [58.6605224609375], "step": 65}, {"value": [57.96771240234375], "step": 66}, {"value": [57.26350784301758], "step": 67}, {"value": [56.564151763916016], "step": 68}, {"value": [55.831661224365234], "step": 69}, {"value": [55.108829498291016], "step": 70}, {"value": [54.37468338012695], "step": 71}, {"value": [53.62167739868164], "step": 72}, {"value": [52.874549865722656], "step": 73}, {"value": [52.11942672729492], "step": 74}, {"value": [51.343204498291016], "step": 75}, {"value": [50.55831527709961], "step": 76}, {"value": [49.788883209228516], "step": 77}]}, "mean_squared_error": {"direction": "min", "observations": [{"value": [9317.2197265625], "step": 0}, {"value": [9264.900390625], "step": 1}, {"value": [9214.8349609375], "step": 2}, {"value": [9165.244140625], "step": 3}, {"value": [9115.9267578125], "step": 4}, {"value": [9066.8740234375], "step": 5}, {"value": [9017.978515625], "step": 6}, {"value": [8969.076171875], "step": 7}, {"value": [8920.1533203125], "step": 8}, {"value": [8871.2109375], "step": 9}, {"value": [8822.22265625], "step": 10}, {"value": [8773.0869140625], "step": 11}, {"value": [8723.849609375], "step": 12}, {"value": [8674.4453125], "step": 13}, {"value": [8624.7265625], "step": 14}, {"value": [8574.60546875], "step": 15}, {"value": [8524.2138671875], "step": 16}, {"value": [8473.4189453125], "step": 17}, {"value": [8422.2236328125], "step": 18}, {"value": [8370.6474609375], "step": 19}, {"value": [8318.5439453125], "step": 20}, {"value": [8265.8603515625], "step": 21}, {"value": [8212.6376953125], "step": 22}, {"value": [8158.86865234375], "step": 23}, {"value": [8104.51318359375], "step": 24}, {"value": [8049.5126953125], "step": 25}, {"value": [7993.8515625], "step": 26}, {"value": [7937.47900390625], "step": 27}, {"value": [7880.43798828125], "step": 28}, {"value": [7822.66943359375], "step": 29}, {"value": [7764.14501953125], "step": 30}, {"value": [7704.87890625], "step": 31}, {"value": [7644.978515625], "step": 32}, {"value": [7584.37646484375], "step": 33}, {"value": [7523.02734375], "step": 34}, {"value": [7460.93115234375], "step": 35}, {"value": [7398.091796875], "step": 36}, {"value": [7334.40478515625], "step": 37}, {"value": [7269.79931640625], "step": 38}, {"value": [7204.30224609375], "step": 39}, {"value": [7137.93408203125], "step": 40}, {"value": [7070.81396484375], "step": 41}, {"value": [7002.98095703125], "step": 42}, {"value": [6934.3603515625], "step": 43}, {"value": [6864.90966796875], "step": 44}, {"value": [6794.783203125], "step": 45}, {"value": [6724.00830078125], "step": 46}, {"value": [6652.6640625], "step": 47}, {"value": [6580.630859375], "step": 48}, {"value": [6508.02490234375], "step": 49}, {"value": [6434.865234375], "step": 50}, {"value": [6361.08935546875], "step": 51}, {"value": [6286.6083984375], "step": 52}, {"value": [6211.6728515625], "step": 53}, {"value": [6136.21142578125], "step": 54}, {"value": [6060.18212890625], "step": 55}, {"value": [5983.54931640625], "step": 56}, {"value": [5906.3916015625], "step": 57}, {"value": [5828.62841796875], "step": 58}, {"value": [5750.525390625], "step": 59}, {"value": [5672.056640625], "step": 60}, {"value": [5593.12890625], "step": 61}, {"value": [5513.79150390625], "step": 62}, {"value": [5433.9892578125], "step": 63}, {"value": [5353.82666015625], "step": 64}, {"value": [5273.34619140625], "step": 65}, {"value": [5192.50048828125], "step": 66}, {"value": [5111.37255859375], "step": 67}, {"value": [5029.9248046875], "step": 68}, {"value": [4947.83447265625], "step": 69}, {"value": [4866.6728515625], "step": 70}, {"value": [4785.212890625], "step": 71}, {"value": [4703.86767578125], "step": 72}, {"value": [4623.80615234375], "step": 73}, {"value": [4543.14013671875], "step": 74}, {"value": [4464.1865234375], "step": 75}, {"value": [4385.46728515625], "step": 76}, {"value": [4306.3212890625], "step": 77}]}, "val_loss": {"direction": "min", "observations": [{"value": [25.208030700683594], "step": 0}, {"value": [25.100027084350586], "step": 1}, {"value": [24.990049362182617], "step": 2}, {"value": [24.8773136138916], "step": 3}, {"value": [24.7625789642334], "step": 4}, {"value": [24.644962310791016], "step": 5}, {"value": [24.523893356323242], "step": 6}, {"value": [24.399673461914062], "step": 7}, {"value": [24.272567749023438], "step": 8}, {"value": [24.141929626464844], "step": 9}, {"value": [24.008129119873047], "step": 10}, {"value": [23.87088394165039], "step": 11}, {"value": [23.729679107666016], "step": 12}, {"value": [23.5832576751709], "step": 13}, {"value": [23.430633544921875], "step": 14}, {"value": [23.271560668945312], "step": 15}, {"value": [23.1060848236084], "step": 16}, {"value": [22.934036254882812], "step": 17}, {"value": [22.75459861755371], "step": 18}, {"value": [22.566062927246094], "step": 19}, {"value": [22.369699478149414], "step": 20}, {"value": [22.166839599609375], "step": 21}, {"value": [21.956607818603516], "step": 22}, {"value": [21.7385311126709], "step": 23}, {"value": [21.512544631958008], "step": 24}, {"value": [21.2768497467041], "step": 25}, {"value": [21.03177261352539], "step": 26}, {"value": [20.77777862548828], "step": 27}, {"value": [20.514238357543945], "step": 28}, {"value": [20.240333557128906], "step": 29}, {"value": [19.955942153930664], "step": 30}, {"value": [19.661495208740234], "step": 31}, {"value": [19.357385635375977], "step": 32}, {"value": [19.0433349609375], "step": 33}, {"value": [18.720266342163086], "step": 34}, {"value": [18.38827896118164], "step": 35}, {"value": [18.04925537109375], "step": 36}, {"value": [17.703990936279297], "step": 37}, {"value": [17.348960876464844], "step": 38}, {"value": [16.98228645324707], "step": 39}, {"value": [16.604202270507812], "step": 40}, {"value": [16.221254348754883], "step": 41}, {"value": [15.870772361755371], "step": 42}, {"value": [15.508064270019531], "step": 43}, {"value": [15.133875846862793], "step": 44}, {"value": [14.752307891845703], "step": 45}, {"value": [14.358859062194824], "step": 46}, {"value": [13.951807975769043], "step": 47}, {"value": [13.530000686645508], "step": 48}, {"value": [13.093844413757324], "step": 49}, {"value": [12.644571304321289], "step": 50}, {"value": [12.187389373779297], "step": 51}, {"value": [11.723531723022461], "step": 52}, {"value": [11.24594497680664], "step": 53}, {"value": [10.754023551940918], "step": 54}, {"value": [10.242776870727539], "step": 55}, {"value": [9.709906578063965], "step": 56}, {"value": [9.172233581542969], "step": 57}, {"value": [8.765355110168457], "step": 58}, {"value": [8.425599098205566], "step": 59}, {"value": [8.082113265991211], "step": 60}, {"value": [7.733470916748047], "step": 61}, {"value": [7.413341522216797], "step": 62}, {"value": [7.132572174072266], "step": 63}, {"value": [6.878482818603516], "step": 64}, {"value": [6.720958232879639], "step": 65}, {"value": [6.582181453704834], "step": 66}, {"value": [6.509056568145752], "step": 67}, {"value": [6.545964241027832], "step": 68}, {"value": [6.711976528167725], "step": 69}, {"value": [6.854798793792725], "step": 70}, {"value": [6.9528937339782715], "step": 71}, {"value": [7.0575852394104], "step": 72}, {"value": [7.171009063720703], "step": 73}, {"value": [7.288486003875732], "step": 74}, {"value": [7.64328145980835], "step": 75}, {"value": [8.090291976928711], "step": 76}, {"value": [8.551401138305664], "step": 77}]}, "val_mean_squared_error": {"direction": "min", "observations": [{"value": [679.90869140625], "step": 0}, {"value": [674.5783081054688], "step": 1}, {"value": [669.1761474609375], "step": 2}, {"value": [663.66943359375], "step": 3}, {"value": [658.0903930664062], "step": 4}, {"value": [652.3927001953125], "step": 5}, {"value": [646.560546875], "step": 6}, {"value": [640.6137084960938], "step": 7}, {"value": [634.5552978515625], "step": 8}, {"value": [628.3497924804688], "step": 9}, {"value": [622.019775390625], "step": 10}, {"value": [615.5675659179688], "step": 11}, {"value": [608.9613647460938], "step": 12}, {"value": [602.1466064453125], "step": 13}, {"value": [595.0792846679688], "step": 14}, {"value": [587.7609252929688], "step": 15}, {"value": [580.206298828125], "step": 16}, {"value": [572.4083862304688], "step": 17}, {"value": [564.3255004882812], "step": 18}, {"value": [555.8936157226562], "step": 19}, {"value": [547.1746215820312], "step": 20}, {"value": [538.2357788085938], "step": 21}, {"value": [529.055908203125], "step": 22}, {"value": [519.6192016601562], "step": 23}, {"value": [509.9324035644531], "step": 24}, {"value": [499.94622802734375], "step": 25}, {"value": [489.68072509765625], "step": 26}, {"value": [479.1706848144531], "step": 27}, {"value": [468.3936462402344], "step": 28}, {"value": [457.33782958984375], "step": 29}, {"value": [446.0163879394531], "step": 30}, {"value": [434.48724365234375], "step": 31}, {"value": [422.7743835449219], "step": 32}, {"value": [410.882568359375], "step": 33}, {"value": [398.8335876464844], "step": 34}, {"value": [386.6453552246094], "step": 35}, {"value": [374.4167175292969], "step": 36}, {"value": [362.1583251953125], "step": 37}, {"value": [349.79107666015625], "step": 38}, {"value": [337.2499084472656], "step": 39}, {"value": [324.560302734375], "step": 40}, {"value": [311.89080810546875], "step": 41}, {"value": [299.15936279296875], "step": 42}, {"value": [286.27215576171875], "step": 43}, {"value": [273.3241882324219], "step": 44}, {"value": [260.517333984375], "step": 45}, {"value": [247.7871856689453], "step": 46}, {"value": [235.09133911132812], "step": 47}, {"value": [222.3925018310547], "step": 48}, {"value": [209.7591552734375], "step": 49}, {"value": [197.2781982421875], "step": 50}, {"value": [185.1097412109375], "step": 51}, {"value": [173.30499267578125], "step": 52}, {"value": [161.7321319580078], "step": 53}, {"value": [150.4480438232422], "step": 54}, {"value": [139.42530822753906], "step": 55}, {"value": [128.69590759277344], "step": 56}, {"value": [118.47473907470703], "step": 57}, {"value": [108.88125610351562], "step": 58}, {"value": [99.9695816040039], "step": 59}, {"value": [91.8743667602539], "step": 60}, {"value": [84.58181762695312], "step": 61}, {"value": [78.10819244384766], "step": 62}, {"value": [72.52484130859375], "step": 63}, {"value": [67.89073944091797], "step": 64}, {"value": [64.23150634765625], "step": 65}, {"value": [61.604217529296875], "step": 66}, {"value": [59.99919128417969], "step": 67}, {"value": [60.13734817504883], "step": 68}, {"value": [63.208702087402344], "step": 69}, {"value": [67.3877182006836], "step": 70}, {"value": [71.7786636352539], "step": 71}, {"value": [77.6589126586914], "step": 72}, {"value": [83.57884216308594], "step": 73}, {"value": [90.8646011352539], "step": 74}, {"value": [102.0939712524414], "step": 75}, {"value": [115.80342864990234], "step": 76}, {"value": [128.90159606933594], "step": 77}]}}}, "score": 6.509056568145752, "best_step": 67, "status": "COMPLETED"}